libFLIR/__init__.py
libFLIR/commands_struct_FLIR.py
libFLIR/configInit.py
libFLIR/libflir.py
libFLIR/serial_FLIR.py
libFLIR-1.4.1.dist-info/DESCRIPTION.rst
libFLIR-1.4.1.dist-info/METADATA
libFLIR-1.4.1.dist-info/RECORD
libFLIR-1.4.1.dist-info/WHEEL
libFLIR-1.4.1.dist-info/metadata.json
libFLIR-1.4.1.dist-info/top_level.txt
