Metadata-Version: 2.0
Name: libFLIR
Version: 1.4.1
Summary: FLIR TAU Control Library
Home-page: https://github.com/weqaar/libflir
Author: Weqaar Janjua
Author-email: weqaar.janjua@gmail.com
License: UNKNOWN
Download-URL: https://github.com/weqaar/libflir/tarball/0.1
Keywords: libflir,thermal,flir
Platform: UNKNOWN
Requires-Dist: crc16 (>=0.1.1)
Requires-Dist: pyserial (>=3.2.1)
